ChangeDotOrgScraper/ChangeDotOrgScraper.py
ChangeDotOrgScraper/__init__.py
ChangeDotOrgScraper-0.0.9.dist-info/LICENSE
ChangeDotOrgScraper-0.0.9.dist-info/METADATA
ChangeDotOrgScraper-0.0.9.dist-info/WHEEL
ChangeDotOrgScraper-0.0.9.dist-info/top_level.txt
ChangeDotOrgScraper-0.0.9.dist-info/RECORD
