Metadata-Version: 2.1
Name: ChangeDotOrgScraper
Version: 0.0.9
Summary: Scrapes online petition data from change.org
Author: Charles Alba
Author-email: alba@wustl.edu
License: MIT
Keywords: change.org,petitions,web scraping
Classifier: Development Status :: 1 - Planning
Classifier: Intended Audience :: Education
Classifier: Intended Audience :: Science/Research
Classifier: Programming Language :: Python :: 3
Classifier: Operating System :: Unix
Classifier: Operating System :: MacOS :: MacOS X
Classifier: Operating System :: Microsoft :: Windows
License-File: LICENSE
Requires-Dist: requests
Requires-Dist: bs4
Requires-Dist: tqdm
Requires-Dist: pandas
Requires-Dist: beautifulsoup4
